setup.py
dummy_test/__init__.py
dummy_test.egg-info/PKG-INFO
dummy_test.egg-info/SOURCES.txt
dummy_test.egg-info/dependency_links.txt
dummy_test.egg-info/not-zip-safe
dummy_test.egg-info/top_level.txt