Metadata-Version: 1.1
Name: dummy-test
Version: 0.1.2
Summary: dummy_test - Dummy test package for testing purposes
Home-page: https://github.com/kienpham2000/dummy_test
Author: Kien Pham
Author-email: kien@sendgrid.com
License: MIT
Keywords: dummy test
Platform: UNKNOWN
Classifier: Development Status :: 5 - Production/Stable
Classifier: Environment :: Console
Classifier: Intended Audience :: Developers
Classifier: License :: OSI Approved :: MIT License
Classifier: Operating System :: OS Independent
Classifier: Programming Language :: Python :: 2
Classifier: Topic :: Software Development :: Quality Assurance
Classifier: Topic :: Software Development :: Testing
